{"propertyAttribute": [{"comment": "", "domain": "", "inverse": "", "equivalent": [""], "minCardinality": "", "label": {"language": "label"}, "range": "", "maxCardinality": "", "subproperty": [""], "attributes": ["deprecated", "external", "datatype", "object", "rdf", "transitive", "functional", "inverse functional", "symmetric"], "cardinality": "", "type": "", "id": ""}, {"range": "n1", "domain": "n2", "id": "e0_0", "label": {"IRI-based": "a", "undefined": "a"}}, {"range": "n1", "domain": "n4", "id": "e1_0", "label": {"IRI-based": "a", "undefined": "a"}}, {"range": "n1", "domain": "n4", "id": "e1_1", "label": {"IRI-based": "b", "undefined": "b"}}, {"range": "n1", "domain": "n5", "id": "e2_0", "label": {"IRI-based": "a", "undefined": "a"}}, {"range": "n6", "domain": "n6", "id": "e3_0", "label": {"IRI-based": "a", "undefined": "a"}}, {"range": "n0", "domain": "n7", "id": "e4_0", "label": {"IRI-based": "i", "undefined": "i"}}, {"range": "n0", "domain": "n7", "id": "e4_1", "label": {"IRI-based": "t", "undefined": "t"}}, {"range": "n0", "domain": "n7", "id": "e4_2", "label": {"IRI-based": ">", "undefined": ">"}}, {"range": "n0", "domain": "n7", "id": "e4_3", "label": {"IRI-based": "<", "undefined": "<"}}, {"range": "n0", "domain": "n7", "id": "e4_4", "label": {"IRI-based": "n", "undefined": "n"}}, {"range": "n1", "domain": "n8", "id": "e5_0", "label": {"IRI-based": "a", "undefined": "a"}}, {"range": "n1", "domain": "n8", "id": "e5_1", "label": {"IRI-based": "b", "undefined": "b"}}, {"range": "n5", "domain": "n9", "id": "e6_0", "label": {"IRI-based": "a", "undefined": "a"}}, {"range": "n10", "domain": "n10", "id": "e7_0", "label": {"IRI-based": "a", "undefined": "a"}}], "datatypeAttribute": [{"comment": "", "equivalent": [""], "label": {"language": "label"}, "iri": "", "individuals": [{"iri": "", "labels": {"language": "label"}, "annotations": {}}], "id": ""}], "datatype": [{"type": "", "id": ""}], "namespace": [{"iri": "", "name": ""}], "metrics": {"individualCount": 0, "methodCount": 8, "datatypePropertyCount": 0, "classCount": 14, "datatypeCount": 0, "axiomCount": 0, "objectPropertyCount": 0, "nodeCount": 0, "propertyCount": 0}, "header": {"description": {"language": "label"}, "author": ["Antonio Sanchez"], "title": {"undefined": "From Smali folder smali_test/", "language": "label"}, "iri": "", "other": {}, "version": "0.1"}, "classAttribute": [{"iri": "http://developer.android.com/reference/android/content/BroadcastReceiver.html", "attributes": ["equivalent"], "id": "sn_0", "label": {"IRI-based": "BroadcastReceiver"}}, {"iri": "http://developer.android.com/intl/es/reference/java/lang/Object.html", "attributes": ["equivalent"], "id": "sn_1", "label": {"IRI-based": "Object"}}, {"iri": "http://developer.android.com/reference/android/app/admin/DeviceAdminReceiver.html", "attributes": ["equivalent"], "id": "sn_2", "label": {"IRI-based": "DeviceAdminReceiver"}}, {"iri": "http://developer.android.com/reference/android/app/Activity.html", "attributes": ["equivalent"], "id": "sn_3", "label": {"IRI-based": "Activity"}}, {"iri": "http://developer.android.com/reference/android/app/Service.html", "attributes": ["equivalent"], "id": "sn_4", "label": {"IRI-based": "Service"}}, {"iri": "http://developer.android.com/reference/android/telephony/PhoneStateListener.html", "attributes": ["equivalent"], "id": "sn_5", "label": {"IRI-based": "PhoneStateListener"}}, {"iri": "https://docs.oracle.com/javase/7/docs/api/java/lang/Thread.html", "attributes": ["equivalent"], "id": "sn_6", "label": {"IRI-based": "Thread"}}, {"iri": "http://developer.android.com/reference/android/os/Binder.html", "attributes": ["equivalent"], "id": "sn_7", "label": {"IRI-based": "Binder"}}, {"attributes": ["equivalent"], "equivalent": ["sn_0"], "id": "n0", "label": {"IRI-based": "com.kk.liushiwu.com.zz.b", "undefined": "com.kk.liushiwu.com.zz.b"}}, {"attributes": ["equivalent"], "equivalent": ["sn_1"], "id": "n1", "label": {"IRI-based": "com.kk.liushiwu.com.zz.c", "undefined": "com.kk.liushiwu.com.zz.c"}}, {"attributes": ["equivalent"], "equivalent": ["sn_2"], "id": "n2", "label": {"IRI-based": "com.kk.liushiwu.com.zz.a", "undefined": "com.kk.liushiwu.com.zz.a"}}, {"attributes": ["equivalent"], "equivalent": ["sn_3"], "id": "n3", "label": {"IRI-based": "com.kk.liushiwu.com.zz.mainActivity", "undefined": "com.kk.liushiwu.com.zz.mainActivity"}}, {"attributes": ["equivalent"], "equivalent": ["sn_4"], "id": "n4", "label": {"IRI-based": "com.kk.liushiwu.com.zz.bs", "undefined": "com.kk.liushiwu.com.zz.bs"}}, {"attributes": ["equivalent"], "equivalent": ["sn_0"], "id": "n5", "label": {"IRI-based": "com.kk.liushiwu.com.zz.pr", "undefined": "com.kk.liushiwu.com.zz.pr"}}, {"attributes": ["equivalent"], "equivalent": ["sn_0"], "id": "n6", "label": {"IRI-based": "com.kk.liushiwu.com.zz.fr", "undefined": "com.kk.liushiwu.com.zz.fr"}}, {"attributes": ["equivalent"], "equivalent": ["sn_4"], "id": "n7", "label": {"IRI-based": "com.kk.liushiwu.com.zz.lanjie", "undefined": "com.kk.liushiwu.com.zz.lanjie"}}, {"attributes": ["equivalent"], "equivalent": ["sn_4"], "id": "n8", "label": {"IRI-based": "com.kk.liushiwu.com.zz.br", "undefined": "com.kk.liushiwu.com.zz.br"}}, {"attributes": ["equivalent"], "equivalent": ["sn_5"], "id": "n9", "label": {"IRI-based": "com.kk.liushiwu.com.zz.d", "undefined": "com.kk.liushiwu.com.zz.d"}}, {"attributes": ["equivalent"], "equivalent": ["sn_6"], "id": "n10", "label": {"IRI-based": "com.kk.liushiwu.com.zz.e", "undefined": "com.kk.liushiwu.com.zz.e"}}, {"attributes": ["equivalent"], "equivalent": ["sn_7"], "id": "n11", "label": {"IRI-based": "com.a.a.a.b", "undefined": "com.a.a.a.b"}}, {"attributes": ["equivalent"], "equivalent": ["sn_1"], "id": "n12", "label": {"IRI-based": "com.a.a.a.c", "undefined": "com.a.a.a.c"}}, {"attributes": ["equivalent"], "equivalent": ["sn_1"], "id": "n13", "label": {"IRI-based": "com.a.a.a.a", "undefined": "com.a.a.a.a"}}], "property": [{"id": ""}, {"type": "owl:objectProperty", "id": "e0_0"}, {"type": "owl:objectProperty", "id": "e1_0"}, {"type": "owl:objectProperty", "id": "e1_1"}, {"type": "owl:objectProperty", "id": "e2_0"}, {"type": "owl:objectProperty", "id": "e3_0"}, {"type": "owl:objectProperty", "id": "e4_0"}, {"type": "owl:objectProperty", "id": "e4_1"}, {"type": "owl:objectProperty", "id": "e4_2"}, {"type": "owl:objectProperty", "id": "e4_3"}, {"type": "owl:objectProperty", "id": "e4_4"}, {"type": "owl:objectProperty", "id": "e5_0"}, {"type": "owl:objectProperty", "id": "e5_1"}, {"type": "owl:objectProperty", "id": "e6_0"}, {"type": "owl:objectProperty", "id": "e7_0"}], "class": [{"type": "Class", "id": "sn_0"}, {"type": "Class", "id": "sn_1"}, {"type": "Class", "id": "sn_2"}, {"type": "Class", "id": "sn_3"}, {"type": "Class", "id": "sn_4"}, {"type": "Class", "id": "sn_5"}, {"type": "Class", "id": "sn_6"}, {"type": "Class", "id": "sn_7"}, {"type": "Class", "id": "n0"}, {"type": "Class", "id": "n1"}, {"type": "Class", "id": "n2"}, {"type": "Class", "id": "n3"}, {"type": "Class", "id": "n4"}, {"type": "Class", "id": "n5"}, {"type": "Class", "id": "n6"}, {"type": "Class", "id": "n7"}, {"type": "Class", "id": "n8"}, {"type": "Class", "id": "n9"}, {"type": "Class", "id": "n10"}, {"type": "Class", "id": "n11"}, {"type": "Class", "id": "n12"}, {"type": "Class", "id": "n13"}]}